moneepay/Monee.py
moneepay/__init__.py
moneepay-1.0.3.dist-info/METADATA
moneepay-1.0.3.dist-info/WHEEL
moneepay-1.0.3.dist-info/RECORD
