Metadata-Version: 2.4
Name: moneepay
Version: 1.0.3
Summary: Library for Python 3+ to accept payments
Project-URL: Homepage, https://github.com/monee-pay/PythonLib
Author-email: Monee <support@monee.pro>
License: MIT License
Keywords: api,payments
Classifier: License :: OSI Approved :: MIT License
Classifier: Programming Language :: Python
Classifier: Programming Language :: Python :: 3
Requires-Python: >=3.7
Requires-Dist: requests
